{
  "tacticId": "CT4",
  "graphVersion": "CT4-v1",
  "entryNodeId": "CT4.entry",
  "nodes": [
    {
      "data": {
        "id": "CT4.entry",
        "label": "Validated CT4 ledger entry",
        "nodeKind": "entry",
        "terminalCase": null,
        "contracts": [
          "S-Def"
        ],
        "leanContract": "StructuralExhaustion.CT4.Nodes.Entry.Contract"
      }
    },
    {
      "data": {
        "id": "CT4.decide.scope",
        "label": "Demand-family scope",
        "nodeKind": "decision",
        "terminalCase": null,
        "contracts": [
          "S-Dich",
          "A-Scope"
        ],
        "leanContract": "StructuralExhaustion.CT4.Nodes.Scope.Contract"
      }
    },
    {
      "data": {
        "id": "CT4.terminal.scope",
        "label": "Missing-demand scope terminal",
        "nodeKind": "terminal",
        "terminalCase": "scope",
        "contracts": [
          "A-Scope"
        ],
        "leanContract": "StructuralExhaustion.CT4.RawOutcome"
      }
    },
    {
      "data": {
        "id": "CT4.certify.assignment",
        "label": "Canonical assignment certification",
        "nodeKind": "certification",
        "terminalCase": null,
        "contracts": [
          "S-Det"
        ],
        "leanContract": "StructuralExhaustion.CT4.Nodes.Assignment.Contract"
      }
    },
    {
      "data": {
        "id": "CT4.decide.availability",
        "label": "Payer availability decision",
        "nodeKind": "decision",
        "terminalCase": null,
        "contracts": [
          "S-Dich",
          "S-Det",
          "S-Rout"
        ],
        "leanContract": "StructuralExhaustion.CT4.Nodes.Availability.Contract"
      }
    },
    {
      "data": {
        "id": "CT4.terminal.ct13",
        "label": "CT13 missing-tier handoff",
        "nodeKind": "terminal",
        "terminalCase": "ct13",
        "contracts": [
          "S-Rout",
          "S-Trig"
        ],
        "leanContract": "StructuralExhaustion.CT4.RawOutcome"
      }
    },
    {
      "data": {
        "id": "CT4.decide.fibres",
        "label": "Fibre-capacity decision",
        "nodeKind": "decision",
        "terminalCase": null,
        "contracts": [
          "S-Dich",
          "S-Comp",
          "S-Rout"
        ],
        "leanContract": "StructuralExhaustion.CT4.Nodes.Fibres.Contract"
      }
    },
    {
      "data": {
        "id": "CT4.terminal.ct9",
        "label": "CT9 overload handoff",
        "nodeKind": "terminal",
        "terminalCase": "ct9",
        "contracts": [
          "S-Rout",
          "S-Trig"
        ],
        "leanContract": "StructuralExhaustion.CT4.RawOutcome"
      }
    },
    {
      "data": {
        "id": "CT4.decide.comparison",
        "label": "Capacity comparison",
        "nodeKind": "decision",
        "terminalCase": null,
        "contracts": [
          "S-Dich",
          "S-Comp"
        ],
        "leanContract": "StructuralExhaustion.CT4.Nodes.Comparison.Contract"
      }
    },
    {
      "data": {
        "id": "CT4.terminal.c4",
        "label": "C4 capacity terminal",
        "nodeKind": "terminal",
        "terminalCase": "c4",
        "contracts": [
          "S-Comp",
          "A-Cert"
        ],
        "leanContract": "StructuralExhaustion.CT4.RawOutcome"
      }
    },
    {
      "data": {
        "id": "CT4.terminal.ct14",
        "label": "CT14 aggregate handoff",
        "nodeKind": "terminal",
        "terminalCase": "ct14",
        "contracts": [
          "S-Rout",
          "S-Trig"
        ],
        "leanContract": "StructuralExhaustion.CT4.RawOutcome"
      }
    }
  ],
  "edges": [
    {
      "data": {
        "id": "CT4.edge.begin",
        "source": "CT4.entry",
        "target": "CT4.decide.scope",
        "kind": "advance",
        "branchTag": "begin",
        "transitionConstructor": "StructuralExhaustion.CT4.Graph.Edge.beginScope",
        "resultConstructor": null,
        "evidence": []
      }
    },
    {
      "data": {
        "id": "CT4.edge.scope.exit",
        "source": "CT4.decide.scope",
        "target": "CT4.terminal.scope",
        "kind": "scope",
        "branchTag": "exit",
        "transitionConstructor": "StructuralExhaustion.CT4.Graph.Edge.scopeExit",
        "resultConstructor": "StructuralExhaustion.CT4.Nodes.Scope.Decision.exit",
        "evidence": [
          {
            "slotId": "candidate",
            "typeExpression": "StructuralExhaustion.CT4.ScopeCandidate framework input"
          }
        ]
      }
    },
    {
      "data": {
        "id": "CT4.edge.scope.ready",
        "source": "CT4.decide.scope",
        "target": "CT4.certify.assignment",
        "kind": "advance",
        "branchTag": "ready",
        "transitionConstructor": "StructuralExhaustion.CT4.Graph.Edge.scopeReady",
        "resultConstructor": "StructuralExhaustion.CT4.Nodes.Scope.Decision.ready",
        "evidence": [
          {
            "slotId": "scopeState",
            "typeExpression": "StructuralExhaustion.CT4.ScopedState framework input"
          }
        ]
      }
    },
    {
      "data": {
        "id": "CT4.edge.assignment.certified",
        "source": "CT4.certify.assignment",
        "target": "CT4.decide.availability",
        "kind": "advance",
        "branchTag": "certified",
        "transitionConstructor": "StructuralExhaustion.CT4.Graph.Edge.assignmentCertified",
        "resultConstructor": null,
        "evidence": [
          {
            "slotId": "assignment",
            "typeExpression": "StructuralExhaustion.CT4.AssignmentState framework input"
          }
        ]
      }
    },
    {
      "data": {
        "id": "CT4.edge.availability.missing",
        "source": "CT4.decide.availability",
        "target": "CT4.terminal.ct13",
        "kind": "handoff",
        "branchTag": "missing",
        "transitionConstructor": "StructuralExhaustion.CT4.Graph.Edge.availabilityMissing",
        "resultConstructor": "StructuralExhaustion.CT4.Nodes.Availability.Decision.missing",
        "evidence": [
          {
            "slotId": "payload",
            "typeExpression": "StructuralExhaustion.CT4.CT13Payload framework input assignment"
          }
        ]
      }
    },
    {
      "data": {
        "id": "CT4.edge.availability.total",
        "source": "CT4.decide.availability",
        "target": "CT4.decide.fibres",
        "kind": "advance",
        "branchTag": "total",
        "transitionConstructor": "StructuralExhaustion.CT4.Graph.Edge.availabilityTotal",
        "resultConstructor": "StructuralExhaustion.CT4.Nodes.Availability.Decision.total",
        "evidence": [
          {
            "slotId": "total",
            "typeExpression": "StructuralExhaustion.CT4.TotalAssignmentState framework input assignment"
          }
        ]
      }
    },
    {
      "data": {
        "id": "CT4.edge.fibres.overloaded",
        "source": "CT4.decide.fibres",
        "target": "CT4.terminal.ct9",
        "kind": "handoff",
        "branchTag": "overloaded",
        "transitionConstructor": "StructuralExhaustion.CT4.Graph.Edge.fibresOverloaded",
        "resultConstructor": "StructuralExhaustion.CT4.Nodes.Fibres.Decision.overloaded",
        "evidence": [
          {
            "slotId": "payload",
            "typeExpression": "StructuralExhaustion.CT4.CT9Payload framework input total"
          }
        ]
      }
    },
    {
      "data": {
        "id": "CT4.edge.fibres.bounded",
        "source": "CT4.decide.fibres",
        "target": "CT4.decide.comparison",
        "kind": "advance",
        "branchTag": "bounded",
        "transitionConstructor": "StructuralExhaustion.CT4.Graph.Edge.fibresBounded",
        "resultConstructor": "StructuralExhaustion.CT4.Nodes.Fibres.Decision.bounded",
        "evidence": [
          {
            "slotId": "bounded",
            "typeExpression": "StructuralExhaustion.CT4.BoundedFibreState framework input total"
          }
        ]
      }
    },
    {
      "data": {
        "id": "CT4.edge.comparison.close",
        "source": "CT4.decide.comparison",
        "target": "CT4.terminal.c4",
        "kind": "close",
        "branchTag": "close",
        "transitionConstructor": "StructuralExhaustion.CT4.Graph.Edge.comparisonClose",
        "resultConstructor": "StructuralExhaustion.CT4.Nodes.Comparison.Decision.close",
        "evidence": [
          {
            "slotId": "certificate",
            "typeExpression": "StructuralExhaustion.CT4.C4Certificate framework input bounded"
          }
        ]
      }
    },
    {
      "data": {
        "id": "CT4.edge.comparison.residual",
        "source": "CT4.decide.comparison",
        "target": "CT4.terminal.ct14",
        "kind": "handoff",
        "branchTag": "residual",
        "transitionConstructor": "StructuralExhaustion.CT4.Graph.Edge.comparisonResidual",
        "resultConstructor": "StructuralExhaustion.CT4.Nodes.Comparison.Decision.residual",
        "evidence": [
          {
            "slotId": "payload",
            "typeExpression": "StructuralExhaustion.CT4.CT14Payload framework input bounded"
          }
        ]
      }
    }
  ]
}
