{
  "artifactType": "tacticInstantiation",
  "schemaVersion": "2.0.0",
  "graphVersion": "CT5-v1",
  "instanceId": "toy-scope",
  "tacticId": "CT5",
  "bindings": [
    {
      "slotId": "framework",
      "leanRef": {
        "module": "StructuralExhaustion.Examples.CT5Toy",
        "declaration": "StructuralExhaustion.Examples.CT5Toy.scopeFramework",
        "sourceFile": "StructuralExhaustion/Examples/CT5Toy.lean",
        "declarationKind": "definition"
      }
    },
    {
      "slotId": "input",
      "leanRef": {
        "module": "StructuralExhaustion.Examples.CT5Toy",
        "declaration": "StructuralExhaustion.Examples.CT5Toy.scopeInput",
        "sourceFile": "StructuralExhaustion/Examples/CT5Toy.lean",
        "declarationKind": "definition"
      }
    },
    {
      "slotId": "corePlan",
      "leanRef": {
        "module": "StructuralExhaustion.Examples.CT5Toy",
        "declaration": "StructuralExhaustion.Examples.CT5Toy.scopePlan",
        "sourceFile": "StructuralExhaustion/Examples/CT5Toy.lean",
        "declarationKind": "definition"
      }
    },
    {
      "slotId": "port",
      "leanRef": {
        "module": "StructuralExhaustion.Examples.CT5Toy",
        "declaration": "StructuralExhaustion.Examples.CT5Toy.scopePort",
        "sourceFile": "StructuralExhaustion/Examples/CT5Toy.lean",
        "declarationKind": "definition"
      }
    },
    {
      "slotId": "handoffPlan",
      "leanRef": {
        "module": "StructuralExhaustion.Examples.CT5Toy",
        "declaration": "StructuralExhaustion.Examples.CT5Toy.scopeHandoff",
        "sourceFile": "StructuralExhaustion/Examples/CT5Toy.lean",
        "declarationKind": "definition"
      }
    }
  ],
  "expectedTerminalCase": "scope",
  "expectedNodePath": [
    "CT5.entry",
    "CT5.decide.scope",
    "CT5.terminal.scope"
  ],
  "expectedEdgePath": [
    "CT5.edge.begin",
    "CT5.edge.scope.exit"
  ],
  "executionResultRef": {
    "module": "StructuralExhaustion.Examples.CT5Toy",
    "declaration": "StructuralExhaustion.Examples.CT5Toy.scopeResult",
    "sourceFile": "StructuralExhaustion/Examples/CT5Toy.lean",
    "declarationKind": "definition"
  },
  "terminalTheoremRef": {
    "module": "StructuralExhaustion.Examples.CT5Toy",
    "declaration": "StructuralExhaustion.Examples.CT5Toy.scope_terminal",
    "sourceFile": "StructuralExhaustion/Examples/CT5Toy.lean",
    "declarationKind": "theorem"
  },
  "traceTheoremRef": {
    "module": "StructuralExhaustion.Examples.CT5Toy",
    "declaration": "StructuralExhaustion.Examples.CT5Toy.scope_trace",
    "sourceFile": "StructuralExhaustion/Examples/CT5Toy.lean",
    "declarationKind": "theorem"
  }
}
